tweetbench/__init__.py
tweetbench/expirements.py
tweetbench/notebook_loader.py
TweetBench_andrewmagill-0.0.2.dist-info/LICENSE
TweetBench_andrewmagill-0.0.2.dist-info/METADATA
TweetBench_andrewmagill-0.0.2.dist-info/WHEEL
TweetBench_andrewmagill-0.0.2.dist-info/top_level.txt
TweetBench_andrewmagill-0.0.2.dist-info/RECORD
