Metadata-Version: 2.1
Name: TweetBench-andrewmagill
Version: 0.0.2
Summary: TweetBench allows you to queue, run, and benchmark Tweet classification expirements with minimal configuration.
Home-page: https://git.txstate.edu/CS7311/a-m730/tree/master/Project/source
Author: Andrew MAgill
Author-email: andrewmagill@txstate.edu
License: UNKNOWN
Platform: UNKNOWN
Classifier: Programming Language :: Python :: 3
Classifier: License :: OSI Approved :: MIT License
Classifier: Operating System :: OS Independent
Requires-Python: >=3.6
Requires-Dist: emoji
Requires-Dist: matplotlib
Requires-Dist: nltk
Requires-Dist: notebook
Requires-Dist: opencv-python
Requires-Dist: pandas
Requires-Dist: pytesseract
Requires-Dist: scikit-learn
